AUTHORS
ChangeLog
LICENSE
README.md
requirements.txt
setup.cfg
setup.py
bettercmd/__init__.py
bettercmd.egg-info/PKG-INFO
bettercmd.egg-info/SOURCES.txt
bettercmd.egg-info/dependency_links.txt
bettercmd.egg-info/not-zip-safe
bettercmd.egg-info/pbr.json
bettercmd.egg-info/requires.txt
bettercmd.egg-info/top_level.txt
examples/basic.py
tests/__init__.py
tests/commands_test.py