Metadata-Version: 1.0
Name: bettercmd
Version: 0.0.2
Summary: A better cmd.py
Home-page: https://github.com/chrisnorman7/
Author: Chris Norman
Author-email: chris.norman2@googlemail.com
License: MPL-2
Platform: UNKNOWN
